LICENSE
README.md
setup.py
pycover/__init__.py
pycover/__version__.py
pycover/binding.py
pycover/environment.py
pycover/exceptions.py
pycover/ffprobe.py
pycover/file_manager.py
pycover/pycover.py
pycover/pycover_session.py
pycover/scaffold.py
pycover/stream_type.py
pycover/sync.py
pycover/version_manager.py
pycover.egg-info/PKG-INFO
pycover.egg-info/SOURCES.txt
pycover.egg-info/dependency_links.txt
pycover.egg-info/not-zip-safe
pycover.egg-info/requires.txt
pycover.egg-info/top_level.txt
pycover/custom_api/__init__.py
pycover/custom_api/custom_api.py
pycover/handlers/__init__.py
pycover/handlers/handlers_holder.py
pycover/media_devices/__init__.py
pycover/media_devices/device_info.py
pycover/media_devices/media_devices.py
pycover/media_devices/screen_info.py
pycover/methods/__init__.py
pycover/methods/core/__init__.py
pycover/methods/core/binding_runner.py
pycover/methods/core/join_voice_call.py
pycover/methods/core/leave_voice_call.py
pycover/methods/core/set_video_call_status.py
pycover/methods/decorators/__init__.py
pycover/methods/decorators/on_closed_voice_chat.py
pycover/methods/decorators/on_group_call_invite.py
pycover/methods/decorators/on_kicked.py
pycover/methods/decorators/on_left.py
pycover/methods/decorators/on_participants_change.py
pycover/methods/decorators/on_raw_update.py
pycover/methods/decorators/on_stream_end.py
pycover/methods/groups/__init__.py
pycover/methods/groups/active_calls.py
pycover/methods/groups/calls.py
pycover/methods/groups/change_volume_call.py
pycover/methods/groups/get_active_call.py
pycover/methods/groups/get_call.py
pycover/methods/groups/get_participants.py
pycover/methods/groups/join_group_call.py
pycover/methods/groups/leave_group_call.py
pycover/methods/handlers/__init__.py
pycover/methods/handlers/raw_update_handler.py
pycover/methods/handlers/stream_ended_handler.py
pycover/methods/stream/__init__.py
pycover/methods/stream/change_stream.py
pycover/methods/stream/mute_stream.py
pycover/methods/stream/pause_stream.py
pycover/methods/stream/played_time.py
pycover/methods/stream/resume_stream.py
pycover/methods/stream/unmute_stream.py
pycover/methods/utilities/__init__.py
